{
  "configVersion": 1,
  "index": "https://venkatjavaji.github.io/ng-pwa/index.html",
  "assetGroups": [
    {
      "name": "app",
      "installMode": "prefetch",
      "updateMode": "prefetch",
      "urls": [
        "https://venkatjavaji.github.io/ng-pwa/favicon.ico",
        "https://venkatjavaji.github.io/ng-pwa/index.html",
        "https://venkatjavaji.github.io/ng-pwa/inline.318b50c57b4eba3d437b.bundle.js",
        "https://venkatjavaji.github.io/ng-pwa/main.d04ca5042acccfb33171.bundle.js",
        "https://venkatjavaji.github.io/ng-pwa/polyfills.f0eca7a3efead95b6d35.bundle.js",
        "https://venkatjavaji.github.io/ng-pwa/styles.ac89bfdd6de82636b768.bundle.css"
      ],
      "patterns": []
    },
    {
      "name": "assets",
      "installMode": "lazy",
      "updateMode": "prefetch",
      "urls": [],
      "patterns": []
    }
  ],
  "dataGroups": [],
  "hashTable": {
    "https://venkatjavaji.github.io/ng-pwa/inline.318b50c57b4eba3d437b.bundle.js": "998c6060446975e566fd17509558ddc68d72eec3",
    "https://venkatjavaji.github.io/ng-pwa/main.d04ca5042acccfb33171.bundle.js": "994176a3e3c1fb021d1566a01ac55b641aa68274",
    "https://venkatjavaji.github.io/ng-pwa/polyfills.f0eca7a3efead95b6d35.bundle.js": "781e0d4ffbf88cd87b5916efa72cb99753d7fe7b",
    "https://venkatjavaji.github.io/ng-pwa/styles.ac89bfdd6de82636b768.bundle.css": "da39a3ee5e6b4b0d3255bfef95601890afd80709",
    "https://venkatjavaji.github.io/ng-pwa/favicon.ico": "84161b857f5c547e3699ddfbffc6d8d737542e01",
    "https://venkatjavaji.github.io/ng-pwa/index.html": "1c5f60e78ba2695aac80f7c671bbc348050750f1"
  }
}